timetracer/__init__.py
timetracer/config.py
timetracer/constants.py
timetracer/context.py
timetracer/exceptions.py
timetracer/pytest_plugin.py
timetracer/session.py
timetracer/types.py
timetracer/cassette/__init__.py
timetracer/cassette/io.py
timetracer/cassette/naming.py
timetracer/catalog/__init__.py
timetracer/cli/__init__.py
timetracer/cli/main.py
timetracer/cli/commands/__init__.py
timetracer/dashboard/__init__.py
timetracer/dashboard/generator.py
timetracer/dashboard/server.py
timetracer/dashboard/template.py
timetracer/diff/__init__.py
timetracer/diff/engine.py
timetracer/diff/report.py
timetracer/integrations/__init__.py
timetracer/integrations/django.py
timetracer/integrations/fastapi.py
timetracer/integrations/flask.py
timetracer/integrations/starlette.py
timetracer/plugins/__init__.py
timetracer/plugins/aiohttp_plugin.py
timetracer/plugins/base.py
timetracer/plugins/httpx_plugin.py
timetracer/plugins/motor_plugin.py
timetracer/plugins/pymongo_plugin.py
timetracer/plugins/redis_plugin.py
timetracer/plugins/requests_plugin.py
timetracer/plugins/sqlalchemy_plugin.py
timetracer/policies/__init__.py
timetracer/policies/capture.py
timetracer/policies/redaction.py
timetracer/replay/__init__.py
timetracer/replay/engine.py
timetracer/replay/errors.py
timetracer/replay/matching.py
timetracer/storage/__init__.py
timetracer/storage/s3.py
timetracer/timeline/__init__.py
timetracer/timeline/generator.py
timetracer/timeline/template.py
timetracer/utils/__init__.py
timetracer/utils/hashing.py
timetracer/utils/time.py
timetracer-1.6.0.dist-info/licenses/LICENSE
timetracer-1.6.0.dist-info/METADATA
timetracer-1.6.0.dist-info/WHEEL
timetracer-1.6.0.dist-info/entry_points.txt
timetracer-1.6.0.dist-info/top_level.txt
timetracer-1.6.0.dist-info/RECORD
