Metadata-Version: 2.4
Name: timetracer
Version: 1.6.0
Summary: Time-travel debugging for FastAPI, Starlette, Flask, and Django - record API cassettes, replay with mocked dependencies
Author: Timetracer Contributors
License: MIT
Project-URL: Homepage, https://github.com/usv240/timetracer
Project-URL: Documentation, https://github.com/usv240/timetracer#readme
Project-URL: Repository, https://github.com/usv240/timetracer
Keywords: fastapi,starlette,flask,django,debugging,testing,pytest,api,replay,mocking,cassette
Classifier: Development Status :: 4 - Beta
Classifier: Intended Audience :: Developers
Classifier: License :: OSI Approved :: MIT License
Classifier: Programming Language :: Python :: 3
Classifier: Programming Language :: Python :: 3.10
Classifier: Programming Language :: Python :: 3.11
Classifier: Programming Language :: Python :: 3.12
Classifier: Framework :: FastAPI
Classifier: Framework :: Flask
Classifier: Topic :: Software Development :: Testing
Classifier: Topic :: Software Development :: Debuggers
Requires-Python: >=3.10
License-File: LICENSE
Provides-Extra: fastapi
Requires-Dist: fastapi>=0.100.0; extra == "fastapi"
Requires-Dist: starlette>=0.27.0; extra == "fastapi"
Provides-Extra: starlette
Requires-Dist: starlette>=0.27.0; extra == "starlette"
Provides-Extra: flask
Requires-Dist: flask>=2.0.0; extra == "flask"
Provides-Extra: httpx
Requires-Dist: httpx>=0.24.0; extra == "httpx"
Provides-Extra: aiohttp
Requires-Dist: aiohttp>=3.8.0; extra == "aiohttp"
Provides-Extra: requests
Requires-Dist: requests>=2.28.0; extra == "requests"
Provides-Extra: sqlalchemy
Requires-Dist: sqlalchemy>=2.0.0; extra == "sqlalchemy"
Provides-Extra: redis
Requires-Dist: redis>=4.0.0; extra == "redis"
Provides-Extra: s3
Requires-Dist: boto3>=1.26.0; extra == "s3"
Provides-Extra: django
Requires-Dist: django>=3.2; extra == "django"
Provides-Extra: motor
Requires-Dist: motor>=3.0.0; extra == "motor"
Provides-Extra: pymongo
Requires-Dist: pymongo>=4.0.0; extra == "pymongo"
Provides-Extra: all
Requires-Dist: timetracer[aiohttp,django,fastapi,flask,httpx,motor,pymongo,redis,requests,s3,sqlalchemy,starlette]; extra == "all"
Provides-Extra: dev
Requires-Dist: timetracer[all]; extra == "dev"
Requires-Dist: pytest>=7.0.0; extra == "dev"
Requires-Dist: pytest-asyncio>=0.21.0; extra == "dev"
Requires-Dist: uvicorn>=0.20.0; extra == "dev"
Requires-Dist: ruff>=0.1.0; extra == "dev"
Requires-Dist: fakeredis>=2.0.0; extra == "dev"
Dynamic: license-file
